common.py
customFronter.py
nonCustomFronter.py
sessionSetup.py
user.py
simplypluralutils-0.1.0.dist-info/licenses/LICENSE
simplypluralutils-0.1.0.dist-info/METADATA
simplypluralutils-0.1.0.dist-info/WHEEL
simplypluralutils-0.1.0.dist-info/top_level.txt
simplypluralutils-0.1.0.dist-info/RECORD
