Metadata-Version: 2.4
Name: simplypluralutils
Version: 0.1.0
Summary: Utilities for working with the Simply Plural API with Python
Requires-Python: >=3.13
License-File: LICENSE
Requires-Dist: requests>=2.32.3
Dynamic: license-file
